yoki/__init__.py
yoki/cli.py
yoki/config.py
yoki/executor.py
yoki/translator.py
yoki/utils.py
yoki_terminal-1.0.1.dist-info/licenses/LICENSE
yoki_terminal-1.0.1.dist-info/METADATA
yoki_terminal-1.0.1.dist-info/WHEEL
yoki_terminal-1.0.1.dist-info/entry_points.txt
yoki_terminal-1.0.1.dist-info/top_level.txt
yoki_terminal-1.0.1.dist-info/RECORD
