Metadata-Version: 2.4
Name: yoki-terminal
Version: 1.0.1
Summary: AI-powered natural language → terminal command converter
Author: Vivek Sharma
License: MIT
Requires-Python: >=3.10
License-File: LICENSE
Requires-Dist: typer>=0.12.0
Requires-Dist: python-dotenv>=1.0.1
Requires-Dist: google-generativeai==0.3.2
Dynamic: license-file
